dbgpt_tugraph_plugins-0.1.1.data/purelib/dbgpt_tugraph_plugins/__init__.py
dbgpt_tugraph_plugins-0.1.1.data/purelib/dbgpt_tugraph_plugins/_version.py
dbgpt_tugraph_plugins-0.1.1.data/purelib/dbgpt_tugraph_plugins/libs/leiden-0.1.1-linux-x86_64.so
dbgpt_tugraph_plugins-0.1.1.dist-info/METADATA
dbgpt_tugraph_plugins-0.1.1.dist-info/WHEEL
dbgpt_tugraph_plugins-0.1.1.dist-info/top_level.txt
dbgpt_tugraph_plugins-0.1.1.dist-info/RECORD
