Metadata-Version: 2.1
Name: dbgpt-tugraph-plugins
Version: 0.1.1
Summary: TuGraph plugins python package used in DB-GPT.
Home-page: https://github.com/TuGraph-family/dbgpt-tugraph-plugins
Author: 
Author-email: 
License: UNKNOWN
Keywords: TuGraph DB-GPT graph LLM
Platform: UNKNOWN
Classifier: Programming Language :: Python :: 3.8
Classifier: Programming Language :: Python :: 3.9
Classifier: Programming Language :: Python :: 3.10
Classifier: Programming Language :: Python :: 3.11
Requires-Python: >=3.8
